nonebot_plugin_ban_sticker/__init__.py
nonebot_plugin_ban_sticker/config.py
nonebot_plugin_ban_sticker-0.1.3.dist-info/licenses/LICENSE
nonebot_plugin_ban_sticker-0.1.3.dist-info/METADATA
nonebot_plugin_ban_sticker-0.1.3.dist-info/WHEEL
nonebot_plugin_ban_sticker-0.1.3.dist-info/top_level.txt
nonebot_plugin_ban_sticker-0.1.3.dist-info/RECORD
