Metadata-Version: 2.4
Name: nonebot-plugin-ban-sticker
Version: 0.1.3
Summary: If you plan to ban sticker in your group chat
License-Expression: MIT
Requires-Python: >=3.9
License-File: LICENSE
Requires-Dist: nonebot-adapter-onebot>=2.4.6
Requires-Dist: nonebot2>=2.4.2
Dynamic: license-file
